{
  "name": "Recetaporcomida",
  "base": "PersistedModel",
  "idInjection": false,
  "options": {
    "validateUpsert": true
  },
  "postgresql": {
    "schema": "public",
    "table": "recetaporcomida"
  },
  "properties": {
    "recetaIdreceta": {
      "type": "Number",
      "id": true,
      "required": true,
      "length": null,
      "precision": 32,
      "scale": 0,
      "postgresql": {
        "columnName": "receta_idreceta",
        "dataType": "integer",
        "dataLength": null,
        "dataPrecision": 32,
        "dataScale": 0,
        "nullable": "NO"
      },
      "_selectable": false
    },
    "comidaIdcomida": {
      "type": "Number",
      "id": true,
      "required": true,
      "length": null,
      "precision": 32,
      "scale": 0,
      "postgresql": {
        "columnName": "comida_idcomida",
        "dataType": "integer",
        "dataLength": null,
        "dataPrecision": 32,
        "dataScale": 0,
        "nullable": "NO"
      },
      "_selectable": false
    }
  },
  "validations": [],
  "relations": {},
  "acls": [],
  "methods": {}
}
